CellCover/__init__.py
CellCover/covering.py
CellCover-0.1.9.dist-info/LICENSE
CellCover-0.1.9.dist-info/METADATA
CellCover-0.1.9.dist-info/WHEEL
CellCover-0.1.9.dist-info/top_level.txt
CellCover-0.1.9.dist-info/RECORD
