Metadata-Version: 2.1
Name: CellCover
Version: 0.1.9
Summary: CellCover
Home-page: UNKNOWN
Author: Laurent Younes
Author-email: <laurent.younes@jhu.edu>
License: UNKNOWN
Keywords: python,single-cell,marker gene
Platform: UNKNOWN
Classifier: Development Status :: 1 - Planning
Classifier: Intended Audience :: Developers
Classifier: Programming Language :: Python :: 3
Classifier: Operating System :: Unix
Classifier: Operating System :: MacOS :: MacOS X
Classifier: Operating System :: Microsoft :: Windows
License-File: LICENSE
Requires-Dist: gurobipy
